many_pynb/__init__.py
many_pynb/__version__.py
many_pynb/main.py
many_pynb-0.1.6.dist-info/METADATA
many_pynb-0.1.6.dist-info/WHEEL
many_pynb-0.1.6.dist-info/top_level.txt
many_pynb-0.1.6.dist-info/RECORD
