Metadata-Version: 2.1
Name: many-pynb
Version: 0.1.6
Summary: Output various settings of jupyter notebook which kernel is python.
Home-page: https://github.com/toshiakiasakura/many_pynb
Author: toshiakiasakura
Author-email: wordpress.akitoshi@gmail.com
License: MIT
Keywords: jupyter notebook papermill ipynb_path html
Platform: UNKNOWN
Classifier: License :: OSI Approved :: MIT License
Classifier: Programming Language :: Python :: 3.7
Requires-Dist: papermill
Requires-Dist: tqdm
